atomic_counter-0.1.4.dist-info/RECORD
atomic_counter-0.1.4.dist-info/WHEEL
atomic_counter-0.1.4.dist-info/METADATA
atomic_counter-0.1.4.dist-info/licenses/LICENSE
atomic_counter/atomic_counter.abi3.so
atomic_counter/__init__.py
atomic_counter/tests/test_exports.py
atomic_counter/tests/test_daily.py
atomic_counter/tests/test_time_counter.py
atomic_counter/tests/test_offset.py
