Metadata-Version: 2.4
Name: atomic-counter
Version: 0.1.4
Classifier: Development Status :: 3 - Alpha
Classifier: Programming Language :: Rust
Classifier: Programming Language :: Python :: Implementation :: CPython
Classifier: Programming Language :: Python :: Implementation :: PyPy
Classifier: Programming Language :: Python :: 3
Classifier: Programming Language :: Python :: 3.8
Classifier: Programming Language :: Python :: 3.9
Classifier: Programming Language :: Python :: 3.10
Classifier: Programming Language :: Python :: 3.11
Requires-Dist: bump-my-version ; extra == 'develop'
Requires-Dist: check-manifest ; extra == 'develop'
Requires-Dist: cibuildwheel ; extra == 'develop'
Requires-Dist: maturin >=1.1, <2 ; extra == 'develop'
Requires-Dist: pytest ; extra == 'develop'
Requires-Dist: pytest-cov ; extra == 'develop'
Requires-Dist: ruff ; extra == 'develop'
Requires-Dist: twine ; extra == 'develop'
Requires-Dist: wheel ; extra == 'develop'
Provides-Extra: develop
License-File: LICENSE
Summary: Atomic Counters
Author: Tim Paine
Requires-Python: >=3.8
Project-URL: repository, https://github.com/timkpaine/atomic-counter
Project-URL: homepage, https://github.com/timkpaine/atomic-counter
